actig_lambda_deployer/__init__.py
actig_lambda_deployer/__main__.py
actig_lambda_deployer/artifact_generator.py
actig_lambda_deployer/aws_clients.py
actig_lambda_deployer/cli.py
actig_lambda_deployer/code_analyzer.py
actig_lambda_deployer/config.py
actig_lambda_deployer/deployment_manager.py
actig_lambda_deployer/tests/__init__.py
actig_lambda_deployer/tests/conftest.py
actig_lambda_deployer/tests/test_code_analyzer.py
actig_lambda_deployer/utils/__init__.py
actig_lambda_deployer/utils/exceptions.py
actig_lambda_deployer/utils/logging.py
actig_lambda_deployer/utils/validation.py
actig_lambda_deployer-0.1.2.dist-info/licenses/LICENSE
actig_lambda_deployer-0.1.2.dist-info/METADATA
actig_lambda_deployer-0.1.2.dist-info/WHEEL
actig_lambda_deployer-0.1.2.dist-info/entry_points.txt
actig_lambda_deployer-0.1.2.dist-info/top_level.txt
actig_lambda_deployer-0.1.2.dist-info/RECORD
