Metadata-Version: 2.4
Name: actig-lambda-deployer
Version: 0.1.2
Summary: AWS Lambda Container Deployment CLI with AI-powered code analysis
Author-email: Dennis Gao <dennisgao2@gmail.com>
License: MIT
Project-URL: Homepage, https://github.com/gao-dennis/actig-lambda-deployer
Project-URL: Repository, https://github.com/gao-dennis/actig-lambda-deployer
Project-URL: Issues, https://github.com/gao-dennis/actig-lambda-deployer/issues
Classifier: Development Status :: 3 - Alpha
Classifier: Intended Audience :: Developers
Classifier: License :: OSI Approved :: MIT License
Classifier: Programming Language :: Python :: 3
Classifier: Programming Language :: Python :: 3.8
Classifier: Programming Language :: Python :: 3.9
Classifier: Programming Language :: Python :: 3.10
Classifier: Programming Language :: Python :: 3.11
Classifier: Programming Language :: Python :: 3.12
Classifier: Topic :: Software Development :: Libraries :: Python Modules
Classifier: Topic :: System :: Systems Administration
Requires-Python: >=3.8
License-File: LICENSE
Requires-Dist: boto3>=1.26.0
Requires-Dist: click>=8.0.0
Requires-Dist: GitPython>=3.1.0
Requires-Dist: python-json-logger>=2.0.0
Requires-Dist: PyYAML>=6.0
Requires-Dist: git-remote-codecommit>=1.15.0
Requires-Dist: pathlib2>=2.3.0; python_version < "3.4"
Provides-Extra: dev
Requires-Dist: pytest>=7.0.0; extra == "dev"
Requires-Dist: pytest-mock>=3.10.0; extra == "dev"
Requires-Dist: pytest-cov>=4.0.0; extra == "dev"
Requires-Dist: black>=22.0.0; extra == "dev"
Requires-Dist: flake8>=5.0.0; extra == "dev"
Requires-Dist: mypy>=1.0.0; extra == "dev"
Requires-Dist: moto>=4.0.0; extra == "dev"
Dynamic: license-file
